parlant_qna/__init__.py
parlant_qna/app.py
parlant_qna/cli.py
parlant_qna/module.py
parlant_qna/server.py
parlant_qna-0.2.3.dist-info/LICENSE
parlant_qna-0.2.3.dist-info/METADATA
parlant_qna-0.2.3.dist-info/WHEEL
parlant_qna-0.2.3.dist-info/entry_points.txt
parlant_qna-0.2.3.dist-info/RECORD
