Metadata-Version: 2.1
Name: parlant-qna
Version: 0.2.3
Summary: A questions and answers tool service for Parlant
License: Apache-2.0
Author: Yam Marcovitz
Author-email: yam@emcie.co
Requires-Python: >=3.10,<4.0
Classifier: License :: OSI Approved :: Apache Software License
Classifier: Programming Language :: Python :: 3
Classifier: Programming Language :: Python :: 3.10
Classifier: Programming Language :: Python :: 3.11
Classifier: Programming Language :: Python :: 3.12
Classifier: Programming Language :: Python :: 3.13
Requires-Dist: colorama (>=0.4.6,<0.5.0)
Requires-Dist: parlant (>=1.4,<2.0)
Requires-Dist: pyright (>=1.1.391,<2.0.0)
Requires-Dist: structlog (>=24.4.0,<25.0.0)
